nextgen_mft/__init__.py
nextgen_mft/ai/__init__.py
nextgen_mft/ai/anomaly.py
nextgen_mft/cli/__init__.py
nextgen_mft/cli/main.py
nextgen_mft/security/__init__.py
nextgen_mft/security/crypto.py
nextgen_mft/transfer/__init__.py
nextgen_mft/transfer/https.py
nextgen_mft/transfer/sftp.py
nextgen_mft-0.2.2.dist-info/METADATA
nextgen_mft-0.2.2.dist-info/WHEEL
nextgen_mft-0.2.2.dist-info/top_level.txt
nextgen_mft-0.2.2.dist-info/RECORD
